lazypip/__init__.py
lazypip/__main__.py
lazypip/app.py
lazypip/cli.py
lazypip/config.py
lazypip/theme.py
lazypip/core/__init__.py
lazypip/core/checker.py
lazypip/core/installer.py
lazypip/core/parser.py
lazypip/core/pip_api.py
lazypip/tui/__init__.py
lazypip/tui/events.py
lazypip/tui/screens/confirmation_dialog.py
lazypip/tui/screens/install_dialog.py
lazypip/tui/screens/install_log.py
lazypip/tui/screens/main.py
lazypip/tui/widgets/footer.py
lazypip/tui/widgets/header.py
lazypip/tui/widgets/package_details.py
lazypip/tui/widgets/package_list.py
lazypip/tui/widgets/status_bar.py
lazypip-0.1.1.dist-info/licenses/LICENSE
lazypip-0.1.1.dist-info/METADATA
lazypip-0.1.1.dist-info/WHEEL
lazypip-0.1.1.dist-info/entry_points.txt
lazypip-0.1.1.dist-info/top_level.txt
lazypip-0.1.1.dist-info/RECORD
